{
  "$schema": "https://mintlify.com/docs.json",
  "theme": "maple",
  "name": "AHS | Documentation",
  "colors": {
    "primary": "#DC2626",
    "light": "#EF4444",
    "dark": "#B91C1C"
  },
  "favicon": "/favicon.svg",
  "navigation": {
    "tabs": [
      {
        "tab": "Game Guide",
        "groups": [
          {
            "group": "Getting Started",
            "pages": [
              "index",
              "player/gameplay-tips",
              "player/school-layout",
              "player/faq"
            ]
          },
          {
            "group": "Emergency Procedures",
            "pages": [
              "emergency/fire-alarm",
              "emergency/lockdown",
              "emergency/communications",
              "player/evacuation"
            ]
          },
          {
            "group": "Rules",
            "pages": [
              "rules/emergency-rules",
              "rules/roleplay",
              "rules/conduct",
              "rules/prohibited"
            ]
          },
          {
            "group": "Player Resources",
            "pages": [
              "player/gameplay-tips",
              "player/school-layout",
              "player/evacuation",
              "player/faq"
            ]
          }
        ]
      },
      {
        "tab": "Staff Resources",
        "groups": [
        {
          "group": "Staff Training",
          "pages": [
            "staff/training",
            "staff/emergency-response"
          ]
        },
        {
          "group": "Management Tools", 
          "pages": [
            "staff/admin-tools",
            "staff/events"
          ]
        }
        ]
      }
    ],
    "global": {
      "anchors": [
        {
          "anchor": "Discord Server",
          "href": "https://Discord.gg/firealarm",
          "icon": "discord"
        },
        {
          "anchor": "Play Game",
          "href": "https://www.roblox.com/games/firealarmschool",
          "icon": "gamepad-2"
        }
      ]
    }
  },
  "logo": {
    "light": "/logo/light.svg",
    "dark": "/logo/dark.svg"
  },
  "navbar": {
    "links": [
      {
        "label": "Discord",
        "href": "https://Discord.gg/firealarm"
      }
    ],
    "primary": {
      "type": "button",
      "label": "Play Game",
      "href": "https://www.roblox.com/games/firealarmschool"
    }
  },
  "contextual": {
    "options": []
  },
  "chat": {
    "enabled": false
  },
  "footer": {
    "socials": {
      "discord": "https://Discord.gg/firealarm",
      "youtube": "https://youtube.com/@firealarmschool",
      "instagram": "https://instagram.com/firealarmschool"
    }
  }
}
